[
  {
    "id": "1",
    "content": "FREE",
    "player_rank": "3",
    "display_start": "0",
    "content_name": "CONTENT_NAME_1"
  },
  {
    "id": "2",
    "content": "SUBPARTY",
    "player_rank": "5",
    "display_start": "0",
    "content_name": "CONTENT_NAME_2"
  },
  {
    "id": "3",
    "content": "EVENT",
    "player_rank": "6",
    "display_start": "0",
    "content_name": "CONTENT_NAME_3"
  },
  {
    "id": "4",
    "content": "JOB",
    "player_rank": "7",
    "display_start": "0",
    "content_name": "CONTENT_NAME_4"
  },
  {
    "id": "5",
    "content": "BACKPARTY",
    "player_rank": "8",
    "display_start": "0",
    "content_name": "CONTENT_NAME_5"
  },
  {
    "id": "6",
    "content": "BLACKSMITH",
    "player_rank": "9",
    "display_start": "0",
    "content_name": "CONTENT_NAME_6"
  },
  {
    "id": "7",
    "content": "SCORECHALLENGE",
    "player_rank": "10",
    "display_start": "0",
    "content_name": "CONTENT_NAME_7"
  },
  {
    "id": "9",
    "content": "EQUIPMENT3",
    "player_rank": "14",
    "display_start": "0",
    "content_name": "CONTENT_NAME_9"
  },
  {
    "id": "10",
    "content": "EQUIPMENT4",
    "player_rank": "18",
    "display_start": "0",
    "content_name": "CONTENT_NAME_10"
  },
  {
    "id": "11",
    "content": "SCORECHALLENGE_EX",
    "player_rank": "45",
    "display_start": "0",
    "content_name": "CONTENT_NAME_11"
  },
  {
    "id": "12",
    "content": "CHARACTER_ENHANCE",
    "player_rank": "30",
    "display_start": "0",
    "content_name": "CONTENT_NAME_12"
  },
  {
    "id": "13",
    "content": "DUNGEON",
    "player_rank": "35",
    "display_start": "0",
    "content_name": "CONTENT_NAME_13"
  },
  {
    "id": "14",
    "content": "SKIP_ALL",
    "player_rank": "25",
    "display_start": "0",
    "content_name": "CONTENT_NAME_14"
  },
  {
    "id": "15",
    "content": "ASSIST",
    "player_rank": "13",
    "display_start": "0",
    "content_name": "CONTENT_NAME_15"
  },
  {
    "id": "16",
    "content": "PARTY_PA_SKILL",
    "player_rank": "12",
    "display_start": "0",
    "content_name": "CONTENT_NAME_16"
  },
  {
    "id": "17",
    "content": "PIECE_BOARD",
    "player_rank": "0",
    "display_start": "2023/1/16 0:00",
    "content_name": "CONTENT_NAME_17"
  },
  {
    "id": "18",
    "content": "FAME_QUEST",
    "player_rank": "13",
    "display_start": "2023/10/10 0:00",
    "content_name": "CONTENT_NAME_18"
  }
]
